MANIFEST.in
README.rst
setup.cfg
setup.py
src/sass.py
src/SassPython.egg-info/PKG-INFO
src/SassPython.egg-info/SOURCES.txt
src/SassPython.egg-info/dependency_links.txt
src/SassPython.egg-info/not-zip-safe
src/SassPython.egg-info/top_level.txt